odoo/addons/agreement_repair/README.rst
odoo/addons/agreement_repair/__init__.py
odoo/addons/agreement_repair/__manifest__.py
odoo/addons/agreement_repair/i18n/agreement_repair.pot
odoo/addons/agreement_repair/i18n/de.po
odoo/addons/agreement_repair/i18n/es.po
odoo/addons/agreement_repair/i18n/es_AR.po
odoo/addons/agreement_repair/i18n/it.po
odoo/addons/agreement_repair/i18n/pt.po
odoo/addons/agreement_repair/i18n/pt_BR.po
odoo/addons/agreement_repair/i18n/sv.po
odoo/addons/agreement_repair/i18n/zh_CN.po
odoo/addons/agreement_repair/models/__init__.py
odoo/addons/agreement_repair/models/agreement.py
odoo/addons/agreement_repair/models/repair.py
odoo/addons/agreement_repair/readme/CONTRIBUTORS.md
odoo/addons/agreement_repair/readme/CREDITS.md
odoo/addons/agreement_repair/readme/DESCRIPTION.md
odoo/addons/agreement_repair/readme/ROADMAP.md
odoo/addons/agreement_repair/readme/USAGE.md
odoo/addons/agreement_repair/static/description/icon.png
odoo/addons/agreement_repair/static/description/index.html
odoo/addons/agreement_repair/tests/__init__.py
odoo/addons/agreement_repair/tests/test_agreement_repair.py
odoo/addons/agreement_repair/views/agreement_view.xml
odoo/addons/agreement_repair/views/repair_view.xml
odoo_addon_agreement_repair-18.0.1.0.0.4.dist-info/METADATA
odoo_addon_agreement_repair-18.0.1.0.0.4.dist-info/WHEEL
odoo_addon_agreement_repair-18.0.1.0.0.4.dist-info/top_level.txt
odoo_addon_agreement_repair-18.0.1.0.0.4.dist-info/RECORD
